tpkg/__init__.py
tpkg/tpkgmodule.py
tpkg-0.1.0.dist-info/METADATA
tpkg-0.1.0.dist-info/WHEEL
tpkg-0.1.0.dist-info/top_level.txt
tpkg-0.1.0.dist-info/RECORD
