Metadata-Version: 2.1
Name: tpkg
Version: 0.1.0
Summary: This package is only for the testing purpose
Home-page: https://github.com/prince-jassi-m/python_package.git
Author: Prince Jassi
Author-email: princejassi@cssoftsolutions.com
Classifier: Programming Language :: Python :: 3
Classifier: License :: OSI Approved :: MIT License
Classifier: Operating System :: OS Independent
Requires-Python: >=3.6
